pyobs_gui/__init__.py
pyobs_gui/base.py
pyobs_gui/camerawidget.py
pyobs_gui/commandinputwidget.py
pyobs_gui/compassmovewidget.py
pyobs_gui/coolingwidget.py
pyobs_gui/datadisplaywidget.py
pyobs_gui/eventswidget.py
pyobs_gui/filterwidget.py
pyobs_gui/fitsheaderswidget.py
pyobs_gui/focuswidget.py
pyobs_gui/gui.py
pyobs_gui/logmodel.py
pyobs_gui/mainwindow.py
pyobs_gui/modewidget.py
pyobs_gui/modulegui.py
pyobs_gui/roofwidget.py
pyobs_gui/shellwidget.py
pyobs_gui/spectrographwidget.py
pyobs_gui/statuswidget.py
pyobs_gui/telescopewidget.py
pyobs_gui/temperaturesplotwidget.py
pyobs_gui/temperatureswidget.py
pyobs_gui/utils.py
pyobs_gui/videowidget.py
pyobs_gui/weatherwidget.py
pyobs_gui/qt/__init__.py
pyobs_gui/qt/camerawidget.ui
pyobs_gui/qt/camerawidget_ui.py
pyobs_gui/qt/compassmoveplugin.py
pyobs_gui/qt/compassmovewidget.py
pyobs_gui/qt/compassmovewidget.ui
pyobs_gui/qt/compassmovewidget_ui.py
pyobs_gui/qt/compile.sh
pyobs_gui/qt/coolingwidget.ui
pyobs_gui/qt/coolingwidget_ui.py
pyobs_gui/qt/datadisplayplugin.py
pyobs_gui/qt/datadisplaywidget.ui
pyobs_gui/qt/datadisplaywidget_ui.py
pyobs_gui/qt/designer.sh
pyobs_gui/qt/eventswidget.ui
pyobs_gui/qt/eventswidget_ui.py
pyobs_gui/qt/filterwidget.ui
pyobs_gui/qt/filterwidget_ui.py
pyobs_gui/qt/fitsheaderswidget.ui
pyobs_gui/qt/fitsheaderswidget_ui.py
pyobs_gui/qt/focuswidget.ui
pyobs_gui/qt/focuswidget_ui.py
pyobs_gui/qt/mainwindow.ui
pyobs_gui/qt/mainwindow_ui.py
pyobs_gui/qt/modewidget.ui
pyobs_gui/qt/modewidget_ui.py
pyobs_gui/qt/resources.qrc
pyobs_gui/qt/resources_rc.py
pyobs_gui/qt/roofwidget.ui
pyobs_gui/qt/roofwidget_ui.py
pyobs_gui/qt/shellwidget.ui
pyobs_gui/qt/shellwidget_ui.py
pyobs_gui/qt/spectrographwidget.ui
pyobs_gui/qt/spectrographwidget_ui.py
pyobs_gui/qt/telescopewidget.ui
pyobs_gui/qt/telescopewidget_ui.py
pyobs_gui/qt/temperaturesplotwidget.ui
pyobs_gui/qt/temperaturesplotwidget_ui.py
pyobs_gui/qt/temperatureswidget.ui
pyobs_gui/qt/temperatureswidget_ui.py
pyobs_gui/qt/videowidget.ui
pyobs_gui-1.6.0.dist-info/METADATA
pyobs_gui-1.6.0.dist-info/WHEEL
pyobs_gui-1.6.0.dist-info/licenses/LICENSE
pyobs_gui-1.6.0.dist-info/RECORD
