Metadata-Version: 2.4
Name: pyobs-gui
Version: 1.6.0
Summary: A remote GUI for pyobs
Author-email: Tim-Oliver Husser <thusser@uni-goettingen.de>
License-Expression: MIT
License-File: LICENSE
Requires-Python: <3.14,>=3.11
Requires-Dist: colour<0.2,>=0.1.5
Requires-Dist: matplotlib<4,>=3.10.1
Requires-Dist: pyobs-core>=1.34.0
Requires-Dist: pyside6>=6.10.1
Requires-Dist: qasync<0.28,>=0.27.1
Requires-Dist: qfitswidget>=0.13.1
Requires-Dist: qtawesome<2,>=1.4.0
Requires-Dist: sunpy<7,>=6.1.1
